alu_wtflags.v
module alu_wtflags(C,OF,ZF,SF,PF,A,B,opcode);
input [7:0] A,B;
input [1:0] opcode;
output reg OF, ZF, SF, PF;
output reg [7:0] C;



always @(*) begin
    case (opcode)
        2'b00: begin
            C = A + B; 
            OF = (A[7] & B[7] & ~C[7]) | (~A[7] & ~B[7] & C[7]);
        end
        2'b01: begin 
            C = A - B; 
            OF = (A[7] & B[7] & ~C[7]) | (~A[7] & ~B[7] & C[7]);
        end
        2'b10: begin
            C = A & B; 
            OF = 0;
        end
        2'b11: begin
            C = A | B; 
            OF = 0;
        end 
    endcase

    ZF = ~|C;
    SF = C[7];
    PF = ~^C;
end
endmodule

alu_wtflags.tb.v
`timescale 1ns/1ps
`include "alu_wtflags.v"

module alu_wtflags_tb;
reg [7:0] A,B;
reg [1:0] opcode;
wire OF, ZF, SF, PF;
wire [7:0] C;

alu_wtflags dut(.C(C), .OF(OF), .ZF(ZF), .SF(SF), .PF(PF), .A(A), .B(B), .opcode(opcode));

initial begin 
    $dumpfile("alu_wtflags.tb.vcd");
    $dumpvars(0,alu_wtflags_tb);
    $display("\t\t Time\t  A\t\t    B  \t    Opcode\tOF\tZF\tSF\tPF\tC");
    $monitor($time, "\t%b\t%b\t%b\t%b\t%b\t%b\t%b\t%b",A,B,opcode,OF,ZF,SF,PF,C);
    #5 A = 8'b00001111; B = 8'b11110000; opcode = 2'b00;
    #5 opcode = 2'b01;
    #5 opcode = 2'b10;
    #5 opcode = 2'b11;
    #5 A = 8'b01010101; B = 8'b10101010; opcode = 2'b00;
    #5 opcode = 2'b01;
    #5 opcode = 2'b10;
    #5 opcode = 2'b11;
    #5 $finish;
end
endmodule

alu_wtflags.tb.vcd
$date
	Mon Oct 27 13:35:18 2025
$end
$version
	Icarus Verilog
$end
$timescale
	1ps
$end
$scope module alu_wtflags_tb $end
$var wire 1 ! ZF $end
$var wire 1 " SF $end
$var wire 1 # PF $end
$var wire 1 $ OF $end
$var wire 8 % C [7:0] $end
$var reg 8 & A [7:0] $end
$var reg 8 ' B [7:0] $end
$var reg 2 ( opcode [1:0] $end
$scope module dut $end
$var wire 8 ) A [7:0] $end
$var wire 8 * B [7:0] $end
$var wire 2 + opcode [1:0] $end
$var reg 8 , C [7:0] $end
$var reg 1 $ OF $end
$var reg 1 # PF $end
$var reg 1 " SF $end
$var reg 1 ! ZF $end
$upscope $end
$upscope $end
$enddefinitions $end
$comment Show the parameter values. $end
$dumpall
$end
#0
$dumpvars
bx ,
bx +
bx *
bx )
bx (
bx '
bx &
bx %
x$
x#
x"
x!
$end
#5000
1#
1"
0!
0$
b11111111 %
b11111111 ,
b0 (
b0 +
b11110000 '
b11110000 *
b1111 &
b1111 )
#10000
0#
0"
b11111 %
b11111 ,
b1 (
b1 +
#15000
1#
1!
b0 %
b0 ,
b10 (
b10 +
#20000
1"
0!
b11111111 %
b11111111 ,
b11 (
b11 +
#25000
b0 (
b0 +
b10101010 '
b10101010 *
b1010101 &
b1010101 )
#30000
0#
b10101011 %
b10101011 ,
b1 (
b1 +
#35000
1#
0"
1!
b0 %
b0 ,
b10 (
b10 +
#40000
1"
0!
b11111111 %
b11111111 ,
b11 (
b11 +
