dff_sy_asy.v
module dff_syn(
    input D, clk, reset,
    output reg Q
);

always @(posedge clk) begin
    if (reset) Q <=1'b0;
    else Q <= D;
end
endmodule

module dff_asyn(
    input D, clk, reset, 
    output reg Q
);

always @(posedge clk or posedge reset) begin
    if (reset) Q <=  1'b0;
    else Q <= D;
end
endmodule

dff_sy_asy.tb.v
`timescale 1ns/1ps
`include "dff_sy_asy.v"

module dff_sy_asy_tb;
reg D, clk, reset;
wire Q;

dff_syn dut1(.D(D), .clk(clk), .reset(reset), .Q(Q));
dff_asyn dut2(.D(D), .clk(clk), .reset(reset), .Q(Q));

initial begin
    clk = 0;
    forever #5 clk = ~clk;
end

initial begin
    $dumpfile("dff_sy_asy.vcd");
    $dumpvars(0,dff_sy_asy_tb);
    $display("\t\tTime\tReset\tD\tQ");
    $monitor($time, "\t%b\t%b\t%b",  reset, D, Q);
    reset = 0; D = 0; 
    #10 D = 1;
    #10 reset = 1; D =0;
    #10 D = 0;
    #10 D = 1;
    #10 D = 1;
    #10 reset = 0; D = 0;
    #10 D = 1;
    #10 D = 1;
    #50 $finish;
end
endmodule

dff_sy_asy.vcd
$date
	Sat Nov 01 11:40:22 2025
$end
$version
	Icarus Verilog
$end
$timescale
	1ps
$end
$scope module dff_sy_asy_tb $end
$var wire 1 ! Q $end
$var reg 1 " D $end
$var reg 1 # clk $end
$var reg 1 $ reset $end
$scope module dut1 $end
$var wire 1 " D $end
$var wire 1 # clk $end
$var wire 1 $ reset $end
$var reg 1 % Q $end
$upscope $end
$scope module dut2 $end
$var wire 1 " D $end
$var wire 1 # clk $end
$var wire 1 $ reset $end
$var reg 1 & Q $end
$upscope $end
$upscope $end
$enddefinitions $end
$comment Show the parameter values. $end
$dumpall
$end
#0
$dumpvars
x&
x%
0$
0#
0"
x!
$end
#5000
0!
0%
0&
1#
#10000
0#
1"
#15000
1%
1!
1&
1#
#20000
x!
0&
0#
0"
1$
#25000
0!
0%
1#
#30000
0#
#35000
1#
#40000
0#
1"
#45000
1#
#50000
0#
#55000
1#
#60000
0#
0"
0$
#65000
1#
#70000
0#
1"
#75000
1%
1!
1&
1#
