edge_detector.v
module edge_detector(
    input clk, reset,
    output reg [7:0] pos_edge, neg_edge
);

reg w;

always @(posedge clk or negedge clk or posedge reset) begin
    if (reset) begin
        pos_edge <= 0;
        neg_edge <= 0;
        w = 0;
    end
    else begin
        if (clk == 1 && w == 0) begin
            pos_edge = pos_edge + 1;
        end
        if (clk == 0 && w == 1) begin
            neg_edge = neg_edge + 1;
        end
        w <= clk;
    end
end
endmodule

edge_detector.tb.v
`timescale 1ns/1ps
`include "edge_detector.v"

module edge_detector_tb;
    reg clk, reset;
    wire [7:0] pos_edge, neg_edge;

edge_detector dut(.clk(clk), .reset(reset), .pos_edge(pos_edge), .neg_edge(neg_edge));

initial begin
    clk = 0;
    forever #5 clk = ~clk;
end

initial begin
    $dumpfile("edge_detector.vcd");
    $dumpvars(0,edge_detector_tb);
    $display("\t\t Time\treset\tPos edge count\tNeg edge count");
    $monitor($time, "\t%b\t\t%d\t\t%d",reset, pos_edge, neg_edge);
    reset = 0; 
    #5 reset = 1;
    #50 reset = 0;
    #50 $finish;
end

endmodule

edge_detector.vcd
$date
	Sat Nov 01 12:10:47 2025
$end
$version
	Icarus Verilog
$end
$timescale
	1ps
$end
$scope module edge_detector_tb $end
$var wire 8 ! pos_edge [7:0] $end
$var wire 8 " neg_edge [7:0] $end
$var reg 1 # clk $end
$var reg 1 $ reset $end
$scope module dut $end
$var wire 1 # clk $end
$var wire 1 $ reset $end
$var reg 8 % neg_edge [7:0] $end
$var reg 8 & pos_edge [7:0] $end
$var reg 1 ' w $end
$upscope $end
$upscope $end
$enddefinitions $end
$comment Show the parameter values. $end
$dumpall
$end
#0
$dumpvars
0'
bx &
bx %
0$
0#
bx "
bx !
$end
#5000
b0 "
b0 %
b0 !
b0 &
1$
1#
#10000
0#
#15000
1#
#20000
0#
#25000
1#
#30000
0#
#35000
1#
#40000
0#
#45000
1#
#50000
0#
#55000
1'
b1 !
b1 &
1#
0$
#60000
0'
b1 "
b1 %
0#
#65000
1'
b10 !
b10 &
1#
#70000
0'
b10 "
b10 %
0#
#75000
1'
b11 !
b11 &
1#
#80000
0'
b11 "
b11 %
0#
#85000
1'
b100 !
b100 &
1#
#90000
0'
b100 "
b100 %
0#
#95000
1'
b101 !
b101 &
1#
#100000
0'
b101 "
b101 %
0#
#105000
1'
b110 !
b110 &
1#
