expilicit_ass_test.v
module explicit_ass_test(A,B,C,D,E,F,Y);
input A,B,C,D,E,F;
output Y;
wire t1,t2,t3,Y;

nand #1 G1(t1,A,B);
and #2 G2(t2,C,~B,D);
nor #1 G3(t3,E,F);
nand #1 G4(Y,t1,t2,t3);
endmodule

expilict_ass_test.tb.v
`timescale 1ns / 1ps
`include "expilicit_ass_test.v"

module expilict_ass_test_tb;
reg X1,X2,X3,X4,X5,X6;
wire OUT;

explicit_ass_test dut(.A(X1),.B(X2),.C(X3),.D(X4),.E(X5),.F(X6),.Y(OUT));

initial begin
    $dumpfile("expilicit_ass_test.vcd");
    $dumpvars(0,expilict_ass_test_tb);
end

initial begin
    $monitor($time,"X1=%b,X2=%b,X3=%b,X4=%b,X5=%b,X6=%b,OUT=%b",X1,X2,X3,X4,X5,X6,OUT);
    #5 X1 = 0; X2 = 0; X3 = 0; X4 = 0; X5 = 0; X6 = 0;
    #5 X1=0; X3=1;
    #5 X1=1; X3=0;
    #5 X6=1; 
    #5 $finish;
end

endmodule

expilicit_ass_test.vcd
$date
	Fri Oct 17 13:03:42 2025
$end
$version
	Icarus Verilog
$end
$timescale
	1ps
$end
$scope module expilict_ass_test_tb $end
$var wire 1 ! OUT $end
$var reg 1 " X1 $end
$var reg 1 # X2 $end
$var reg 1 $ X3 $end
$var reg 1 % X4 $end
$var reg 1 & X5 $end
$var reg 1 ' X6 $end
$scope module dut $end
$var wire 1 " A $end
$var wire 1 # B $end
$var wire 1 $ C $end
$var wire 1 % D $end
$var wire 1 & E $end
$var wire 1 ' F $end
$var wire 1 ! Y $end
$var wire 1 ( t1 $end
$var wire 1 ) t2 $end
$var wire 1 * t3 $end
$upscope $end
$upscope $end
$enddefinitions $end
$comment Show the parameter values. $end
$dumpall
$end
#0
$dumpvars
x*
x)
x(
x'
x&
x%
x$
x#
x"
x!
$end
#5000
0'
0&
0%
0$
0#
0"
#6000
1*
1(
#7000
0)
#8000
1!
#10000
1$
#15000
0$
1"
#20000
1'
#21000
0*
