full_adder.v
module full_adder (a,b,c,s,ca);
input a,b,c;
output reg s,ca;

always@(*) begin
    {ca,s}=a+b+c;
end

endmodule

full_adder.tb.v
`timescale 1ns/1ps
`include "full_adder.v"
module full_adder_tb;
reg a,b,c;
wire s,ca;

full_adder dut(a,b,c,s,ca);
reg [3:0]i;
initial begin
    $display("a\tb\tc\t Sum\tCarry");
    $dumpfile("full_adder.tb.vcd");
    $dumpvars(0, full_adder_tb);

    for (i=0; i<8; i=i+1) begin
        {a,b,c}=i;
        #1;
        $display("%b\t%b\t%b\t %b\t%b",a,b,c,s,ca);
    end
    $finish;
end

endmodule

full_adder.tb.vcd
$date
	Thu Oct 23 14:02:53 2025
$end
$version
	Icarus Verilog
$end
$timescale
	1ps
$end
$scope module full_adder_tb $end
$var wire 1 ! s $end
$var wire 1 " ca $end
$var reg 1 # a $end
$var reg 1 $ b $end
$var reg 1 % c $end
$var reg 4 & i [3:0] $end
$scope module dut $end
$var wire 1 # a $end
$var wire 1 $ b $end
$var wire 1 % c $end
$var reg 1 " ca $end
$var reg 1 ! s $end
$upscope $end
$upscope $end
$enddefinitions $end
$comment Show the parameter values. $end
$dumpall
$end
#0
$dumpvars
b0 &
0%
0$
0#
0"
0!
$end
#1000
1!
1%
b1 &
#2000
1$
0%
b10 &
#3000
1"
0!
1%
b11 &
#4000
0"
1!
1#
0$
0%
b100 &
#5000
1"
0!
1%
b101 &
#6000
1$
0%
b110 &
#7000
1!
1%
b111 &
#8000
b1000 &
