gate_test.v
module gate_test(A,B,C,D,E,F,Y);

    input A,B,C,D,E,F;
    output Y;
    wire t1,t2,t3,Y;

    nand #1 G1(t1,A,B);
    and #2 G2(t2,C,~B,D);
    nor #1 G3(t3,E,F);
    nand #1 G4(Y,t1,t2,t3);

endmodule

gate_test.tb.v
`timescale 1ns/1ps
`include "gate_test.v"

module gate_test_tb;
    reg A,B,C,D,E,F;
    wire Y;
    gate_test DUT(A,B,C,D,E,F,Y);
    initial begin
        $dumpfile("gate_test.vpp");
        $dumpvars(0, gate_test_tb);
        $monitor($time,"A=%b,B=%b,C=%b,D=%d,E=%b,F=%b,Y=%b",A,B,C,D,E,F,Y);
        #5 A=1; B=0; C=0; D=1; E=0; F=0;
        #5 A=0; B=0; C=1; D=1; E=0; F=0;
        #5 A=1; C=0;
        #5 F=1;
        #5 $finish;
    end
endmodule

gate_test.vcd
$date
	Fri Oct 17 11:02:38 2025
$end
$version
	Icarus Verilog
$end
$timescale
	1ps
$end
$scope module gate_test_tb $end
$var wire 1 ! Y $end
$var reg 1 " A $end
$var reg 1 # B $end
$var reg 1 $ C $end
$var reg 1 % D $end
$var reg 1 & E $end
$var reg 1 ' F $end
$scope module DUT $end
$var wire 1 " A $end
$var wire 1 # B $end
$var wire 1 $ C $end
$var wire 1 % D $end
$var wire 1 & E $end
$var wire 1 ' F $end
$var wire 1 ! Y $end
$var wire 1 ( t1 $end
$var wire 1 ) t2 $end
$var wire 1 * t3 $end
$upscope $end
$upscope $end
$enddefinitions $end
$comment Show the parameter values. $end
$dumpall
$end
#0
$dumpvars
x*
x)
x(
x'
x&
x%
x$
x#
x"
x!
$end
#5000
0'
0&
1%
0$
0#
1"
#6000
1*
1(
#7000
0)
#8000
1!
#10000
1$
0"
#12000
1)
#13000
0!
#15000
0$
1"
#17000
0)
#18000
1!
#20000
1'
#21000
0*
