jkff_stru.v
/*module sr_latch(
    input S,R,
    output Q,Qbar
);

nand G1(Q, R, Qbar);
nand G2(Qbar, S, Q);
endmodule

module jkff_stru(
    input J,K,clk,reset,
    output Q,Qbar
);

wire [7:0]w;

nand G1(w[0], J, Qbar,  clk);
nand G2(w[1], K, Q, clk);

assign w[2] = (reset) ? 1'b0 : w[0];
assign w[3] = (reset) ? 1'b1 : w[1];

sr_latch SR1(.S(w[2]), .R(w[3]), .Q(w[4]), .Qbar(w[5]));

assign w[6] = (reset) ? 1'b0 : w[4];
assign w[7] = (reset) ? 1'b1 : w[5];

sr_latch SR2(.S(w[6]), .R(w[7]), .Q(Q), .Qbar(Qbar));

endmodule
*/

module sr_latch(
    input S, R,
    output Q, Qbar
);
    nand G1(Q, R, Qbar);
    nand G2(Qbar, S, Q);
endmodule

module jkff_stru(
    input J, K, clk, reset,
    output Q, Qbar
);
    wire w_master, w_master_bar;

    
    wire S_master, R_master;
    assign S_master = reset ? 1'b1 : ~(J & Qbar & clk); 
    assign R_master = reset ? 1'b0 : ~(K & Q & clk);


    sr_latch master(.S(S_master), .R(R_master), .Q(w_master), .Qbar(w_master_bar));

    
    wire S_slave, R_slave;
    assign S_slave = reset ? 1'b0 : w_master;     
    assign R_slave = reset ? 1'b1 : w_master_bar;   

    
    sr_latch slave(.S(S_slave), .R(R_slave), .Q(Q), .Qbar(Qbar));
endmodule

jkff_stru.tb.v
/*`timescale 1ns/1ps
`include "jkff_stru.v"

module jkff_stru_tb;
reg J,K,clk;
wire Q,Qbar;

jkff_stru dut(.J(J), .K(K), .clk(clk), .Q(Q), .Qbar(Qbar));

integer i;

initial begin
    clk = 0;
    forever #5 clk = ~clk;
end

initial begin
    $dumpfile("jkff_stru.vcd");
    $dumpvars(0, jkff_stru_tb);
    $display("\t\tTime\tJ\tK\tQ\tQbar");
    $monitor($time, "\t%b\t%b\t%b\t%b", J,K,Q,Qbar);
    J = 0; K = 0; 
    #5;
    for (i = 0; i < 4; i++) begin
        {J,K} = i;
        @(posedge clk);`timescale 1ns/1ps
        #5;
    end
    #5 $finish;
end
endmodule
*/

`timescale 1ns/1ps
`include "jkff_stru.v"

module jkff_stru_tb;
reg J,K,clk,reset;
wire Q,Qbar;

jkff_stru dut(.J(J), .K(K), .clk(clk), .reset(reset), .Q(Q), .Qbar(Qbar));

integer i;

initial begin
    clk = 0;
    forever #5 clk = ~clk;
end

initial begin
    $dumpfile("jkff_stru.vcd");
    $dumpvars(0,jkff_stru_tb);
    $display("\t\tTime\tJ\tK\tQ\tQbar");
    $monitor($time, "\t%b\t%b\t%b\t%b",J,K,Q,Qbar);
    reset = 1; J = 0; K = 0; 
    #5 reset = 0;
    for (i=0; i<4; i++) begin
        {J,K} = i;
        @(posedge clk);
        #5;
    end
    #5 $finish;
end
endmodule

jkff_stru.vcd
$date
	Fri Oct 31 17:40:21 2025
$end
$version
	Icarus Verilog
$end
$timescale
	1ps
$end
$scope module jkff_stru_tb $end
$var wire 1 ! Qbar $end
$var wire 1 " Q $end
$var reg 1 # J $end
$var reg 1 $ K $end
$var reg 1 % clk $end
$var reg 1 & reset $end
$var integer 32 ' i [31:0] $end
$scope module dut $end
$var wire 1 # J $end
$var wire 1 $ K $end
$var wire 1 % clk $end
$var wire 1 & reset $end
$var wire 1 ( w_master_bar $end
$var wire 1 ) w_master $end
$var wire 1 * S_slave $end
$var wire 1 + S_master $end
$var wire 1 , R_slave $end
$var wire 1 - R_master $end
$var wire 1 ! Qbar $end
$var wire 1 " Q $end
$scope module master $end
$var wire 1 ) Q $end
$var wire 1 ( Qbar $end
$var wire 1 - R $end
$var wire 1 + S $end
$upscope $end
$scope module slave $end
$var wire 1 " Q $end
$var wire 1 ! Qbar $end
$var wire 1 , R $end
$var wire 1 * S $end
$upscope $end
$upscope $end
$upscope $end
$enddefinitions $end
$comment Show the parameter values. $end
$dumpall
$end
#0
$dumpvars
0-
1,
1+
0*
1)
0(
bx '
1&
0%
0$
0#
0"
1!
$end
#5000
0!
1"
1-
1*
0,
b0 '
0&
1%
#10000
0%
#15000
1%
#20000
1$
b1 '
0%
#25000
0-
1%
#30000
1-
1#
0$
b10 '
0%
#35000
1%
#40000
1$
b11 '
0%
#45000
0-
1%
#50000
1-
b100 '
0%
#55000
0-
1%
