johnson_4bit.v
module johnson_4bit(
    input clk, reset,
    output reg [3:0]count
);

always @(posedge clk or posedge reset) begin
    if (reset) count <= 4'b0000;
    else count <= {~count[0],count[3:1]};
end
endmodule

johnson_4bit.tb.v
`timescale 1ns/1ps
`include "johnson_4bit.v"

module johnson_4bit_tb;
reg clk, reset;
wire [3:0]count;

johnson_4bit dut(.clk(clk), .reset(reset), .count(count));

initial begin
    clk = 0;
    forever #5 clk = ~clk;
end

initial begin
    $dumpfile("johnson_4bit.vcd");
    $dumpvars(0,johnson_4bit_tb);
    $display("\t\tTime\treset\tCount");
    $monitor($time, "\t%b\t%b",reset, count);
    reset = 1;
    #5 reset = 0;
    #100;
    $finish;
end
endmodule

johnson_4bit.vcd
$date
	Mon Nov 03 16:05:53 2025
$end
$version
	Icarus Verilog
$end
$timescale
	1ps
$end
$scope module johnson_4bit_tb $end
$var wire 4 ! count [3:0] $end
$var reg 1 " clk $end
$var reg 1 # reset $end
$scope module dut $end
$var wire 1 " clk $end
$var wire 1 # reset $end
$var reg 4 $ count [3:0] $end
$upscope $end
$upscope $end
$enddefinitions $end
$comment Show the parameter values. $end
$dumpall
$end
#0
$dumpvars
b0 $
1#
0"
b0 !
$end
#5000
b1000 !
b1000 $
0#
1"
#10000
0"
#15000
b1100 !
b1100 $
1"
#20000
0"
#25000
b1110 !
b1110 $
1"
#30000
0"
#35000
b1111 !
b1111 $
1"
#40000
0"
#45000
b111 !
b111 $
1"
#50000
0"
#55000
b11 !
b11 $
1"
#60000
0"
#65000
b1 !
b1 $
1"
#70000
0"
#75000
b0 !
b0 $
1"
#80000
0"
#85000
b1000 !
b1000 $
1"
#90000
0"
#95000
b1100 !
b1100 $
1"
#100000
0"
#105000
b1110 !
b1110 $
1"
