mux2x1_dataflow.v
module mux2x1_dataflow(out,data_in,sel) ;
input [1:0] data_in;
input sel;
output out;

assign out = (sel) ? data_in[0] : data_in[1];

endmodule

mux2x1_dataflow.tb.v
`timescale 1ns/1ps
`include "mux2x1_dataflow.v"

module mux2x1_dataflow_tb;
reg [1:0] data_in;
reg sel;
wire out;

mux2x1_dataflow dut(out,data_in,sel);
initial begin
    $dumpfile("mux2x1_dataflow.tb.vcd");
    $dumpvars(0,mux2x1_dataflow_tb);
    $monitor($time, "data_in = %b, select = %b, out = %b",data_in, sel, out);
    #5 data_in = 2'b00; sel = 1'b0;
    #5 sel = 1'b1;
    #5 data_in = 2'b01; sel = 1'b0;
    #5 sel = 1'b1;
    #5 data_in = 2'b10; sel = 1'b0;
    #5 sel = 1'b1;
    #5 data_in = 2'b11; sel = 1'b0;
    #5 sel = 1'b1;
    #5 $finish;
end
endmodule

mux2x1_dataflow.tb.vcd
$date
	Mon Oct 27 09:36:02 2025
$end
$version
	Icarus Verilog
$end
$timescale
	1ps
$end
$scope module mux2x1_dataflow_tb $end
$var wire 1 ! out $end
$var reg 2 " data_in [1:0] $end
$var reg 1 # sel $end
$scope module dut $end
$var wire 2 $ data_in [1:0] $end
$var wire 1 # sel $end
$var wire 1 ! out $end
$upscope $end
$upscope $end
$enddefinitions $end
$comment Show the parameter values. $end
$dumpall
$end
#0
$dumpvars
bx $
x#
bx "
x!
$end
#5000
0!
0#
b0 "
b0 $
#10000
1#
#15000
0#
b1 "
b1 $
#20000
1!
1#
#25000
0#
b10 "
b10 $
#30000
0!
1#
#35000
1!
0#
b11 "
b11 $
#40000
1#
