mux3x1.v
module mux3x1(
    input [2:0]in,
    input [1:0]sel,
    output reg out
);

always @(*) begin
    case (sel)
    2'b00 : out = in[0];
    2'b01 : out = in[1];
    2'b10 : out = in[2];
    default : out = 1'bx;    
    endcase
end

endmodule

mux3x1.tb.v
`timescale 1ns/1ps
`include "mux3x1.v"

module mux3x1_tb;
reg [2:0]in;
reg [1:0]sel;
wire out;

mux3x1 dut(.in(in), .sel(sel), .out(out));

initial begin
    $dumpfile("mux3x1.vcd");
    $dumpvars(0,mux3x1_tb);
    $display("\t\tTime\tSelect\tIn\tOut");
    $monitor($time, "\t%b\t%b\t%b", sel, in, out);
    #5 in = 3'b 010; sel = 2'b00;
    #5 sel = 2'b01;
    #5 sel = 2'b10;
    #5 sel = 2'b11;
    #5 in = 3'b101; sel = 2'b00;
    #5 sel = 2'b01;
    #5 sel = 2'b10;
    #5 sel = 2'b11;
    #10 $finish;
end

endmodule

mux3x1.vcd
$date
	Mon Nov 03 09:25:44 2025
$end
$version
	Icarus Verilog
$end
$timescale
	1ps
$end
$scope module mux3x1_tb $end
$var wire 1 ! out $end
$var reg 3 " in [2:0] $end
$var reg 2 # sel [1:0] $end
$scope module dut $end
$var wire 3 $ in [2:0] $end
$var wire 2 % sel [1:0] $end
$var reg 1 ! out $end
$upscope $end
$upscope $end
$enddefinitions $end
$comment Show the parameter values. $end
$dumpall
$end
#0
$dumpvars
bx %
bx $
bx #
bx "
x!
$end
#5000
0!
b0 #
b0 %
b10 "
b10 $
#10000
1!
b1 #
b1 %
#15000
0!
b10 #
b10 %
#20000
x!
b11 #
b11 %
#25000
1!
b0 #
b0 %
b101 "
b101 $
#30000
0!
b1 #
b1 %
#35000
1!
b10 #
b10 %
#40000
x!
b11 #
b11 %
