mux4x1_dataflow.v
module mux4x1_dataflow(out, data_in, sel);
input [3:0]data_in;
input [1:0]sel;
output out;

assign out = (sel == 2'b00) ? data_in[0] 
           : (sel == 2'b01) ? data_in[1] 
           : (sel == 2'b10) ? data_in[2] 
           : data_in[3];

endmodule

mux4x1_dataflow.tb.v
`timescale 1ns/1ps
`include "mux4x1_dataflow.v"

module mux4x1_dataflow_tb;
reg [3:0]data_in;
reg [1:0]sel;
wire out;

integer i, j;

mux4x1_dataflow dut (.out(out), .data_in(data_in), .sel(sel));
initial begin
    $dumpfile("mux4x1_dataflow.tb.vcd");
    $dumpvars(0,mux4x1_dataflow_tb);
    $display("\t\tTime\tInput\tSelect\tOutput");
    $monitor($time, "\t%b\t%b\t%b",data_in,sel,out);
    for(i = 0; i < 16; i++) begin
        data_in = i;
        for(j = 0; j < 4; j++) begin
            sel = j;
            #5;
        end
    end 
    #5 $finish;
end
endmodule

mux4x1_dataflow.tb.vcd
$date
	Mon Oct 27 11:13:46 2025
$end
$version
	Icarus Verilog
$end
$timescale
	1ps
$end
$scope module mux4x1_dataflow_tb $end
$var wire 1 ! out $end
$var reg 4 " data_in [3:0] $end
$var reg 2 # sel [1:0] $end
$var integer 32 $ i [31:0] $end
$var integer 32 % j [31:0] $end
$scope module dut $end
$var wire 4 & data_in [3:0] $end
$var wire 2 ' sel [1:0] $end
$var wire 1 ! out $end
$upscope $end
$upscope $end
$enddefinitions $end
$comment Show the parameter values. $end
$dumpall
$end
#0
$dumpvars
b0 '
b0 &
b0 %
b0 $
b0 #
b0 "
0!
$end
#5000
b1 #
b1 '
b1 %
#10000
b10 #
b10 '
b10 %
#15000
b11 #
b11 '
b11 %
#20000
1!
b0 #
b0 '
b1 "
b1 &
b1 $
b0 %
#25000
0!
b1 #
b1 '
b1 %
#30000
b10 #
b10 '
b10 %
#35000
b11 #
b11 '
b11 %
#40000
b0 #
b0 '
b10 "
b10 &
b10 $
b0 %
#45000
1!
b1 #
b1 '
b1 %
#50000
0!
b10 #
b10 '
b10 %
#55000
b11 #
b11 '
b11 %
#60000
1!
b0 #
b0 '
b11 "
b11 &
b11 $
b0 %
#65000
b1 #
b1 '
b1 %
#70000
0!
b10 #
b10 '
b10 %
#75000
b11 #
b11 '
b11 %
#80000
b0 #
b0 '
b100 "
b100 &
b100 $
b0 %
#85000
b1 #
b1 '
b1 %
#90000
1!
b10 #
b10 '
b10 %
#95000
0!
b11 #
b11 '
b11 %
#100000
1!
b0 #
b0 '
b101 "
b101 &
b101 $
b0 %
#105000
0!
b1 #
b1 '
b1 %
#110000
1!
b10 #
b10 '
b10 %
#115000
0!
b11 #
b11 '
b11 %
#120000
b0 #
b0 '
b110 "
b110 &
b110 $
b0 %
#125000
1!
b1 #
b1 '
b1 %
#130000
b10 #
b10 '
b10 %
#135000
0!
b11 #
b11 '
b11 %
#140000
1!
b0 #
b0 '
b111 "
b111 &
b111 $
b0 %
#145000
b1 #
b1 '
b1 %
#150000
b10 #
b10 '
b10 %
#155000
0!
b11 #
b11 '
b11 %
#160000
b0 #
b0 '
b1000 "
b1000 &
b1000 $
b0 %
#165000
b1 #
b1 '
b1 %
#170000
b10 #
b10 '
b10 %
#175000
1!
b11 #
b11 '
b11 %
#180000
b0 #
b0 '
b1001 "
b1001 &
b1001 $
b0 %
#185000
0!
b1 #
b1 '
b1 %
#190000
b10 #
b10 '
b10 %
#195000
1!
b11 #
b11 '
b11 %
#200000
0!
b0 #
b0 '
b1010 "
b1010 &
b1010 $
b0 %
#205000
1!
b1 #
b1 '
b1 %
#210000
0!
b10 #
b10 '
b10 %
#215000
1!
b11 #
b11 '
b11 %
#220000
b0 #
b0 '
b1011 "
b1011 &
b1011 $
b0 %
#225000
b1 #
b1 '
b1 %
#230000
0!
b10 #
b10 '
b10 %
#235000
1!
b11 #
b11 '
b11 %
#240000
0!
b0 #
b0 '
b1100 "
b1100 &
b1100 $
b0 %
#245000
b1 #
b1 '
b1 %
#250000
1!
b10 #
b10 '
b10 %
#255000
b11 #
b11 '
b11 %
#260000
b0 #
b0 '
b1101 "
b1101 &
b1101 $
b0 %
#265000
0!
b1 #
b1 '
b1 %
#270000
1!
b10 #
b10 '
b10 %
#275000
b11 #
b11 '
b11 %
#280000
0!
b0 #
b0 '
b1110 "
b1110 &
b1110 $
b0 %
#285000
1!
b1 #
b1 '
b1 %
#290000
b10 #
b10 '
b10 %
#295000
b11 #
b11 '
b11 %
#300000
b0 #
b0 '
b1111 "
b1111 &
b1111 $
b0 %
#305000
b1 #
b1 '
b1 %
#310000
b10 #
b10 '
b10 %
#315000
b11 #
b11 '
b11 %
#320000
b10000 $
b100 %
