position_asso_test.v
module position_asso_test(A,B,C,D,E,F,Y);
input A,B,C,D,E,F;
output Y;
wire t1,t2,t3,Y;

nand #1 G1(t1,A,B);
and #2 G2(t2,C,~B,D);
nor #1 G3(t3,E,F);
nand #1 G4(Y,t1,t2,t3);
endmodule

position_ass_test.tb.v
`timescale 1ns / 1ps
`include "position_asso_test.v"

module position_ass_test_tb;
    reg X1,X2,X3,X4,X5,X6;
    wire OUT;
    position_asso_test dut (X1,X2,X3,X4,X5,X6,OUT);
        initial begin
            $dumpfile("position_aso_test.vcd");
            $dumpvars(0,position_ass_test_tb);
            $monitor($time,"X1=%b,X2=%b,X3=%b,X4=%b,X5=%b,X6=%b,OUT=%b",X1,X2,X3,X4,X5,X6,OUT);
            #5 X1=1;X2=0;X3=0;X4=1;X5=0;X6=1;
            #5 X1=0; X3=1;
            #5 X1=1; X3=0;
            #5 X6=1;
            #5 $finish;
        end
endmodule

position_aso_test.vcd
$date
	Fri Oct 17 12:46:44 2025
$end
$version
	Icarus Verilog
$end
$timescale
	1ps
$end
$scope module position_ass_test_tb $end
$var wire 1 ! OUT $end
$var reg 1 " X1 $end
$var reg 1 # X2 $end
$var reg 1 $ X3 $end
$var reg 1 % X4 $end
$var reg 1 & X5 $end
$var reg 1 ' X6 $end
$scope module dut $end
$var wire 1 " A $end
$var wire 1 # B $end
$var wire 1 $ C $end
$var wire 1 % D $end
$var wire 1 & E $end
$var wire 1 ' F $end
$var wire 1 ! Y $end
$var wire 1 ( t1 $end
$var wire 1 ) t2 $end
$var wire 1 * t3 $end
$upscope $end
$upscope $end
$enddefinitions $end
$comment Show the parameter values. $end
$dumpall
$end
#0
$dumpvars
x*
x)
x(
x'
x&
x%
x$
x#
x"
x!
$end
#5000
1'
0&
1%
0$
0#
1"
#6000
0*
1(
#7000
1!
0)
#10000
1$
0"
#12000
1)
#15000
0$
1"
#17000
0)
