shift_reg_8bit.v
module dff_stru(
    input D, clk, reset,
    output reg Q
);

always @(posedge clk or posedge reset) begin
    if (reset) Q <= 1'b0;
    else Q <= D;
end

endmodule

module shift_reg_8bit(
    input clk, reset, en, serial_in,
    output serial_out
);

integer i;

reg [7:0] w;
wire [7:0] q;

assign serial_out = q[0];

always @(posedge clk or posedge reset) begin
    if (en) begin
        w[7] <= serial_in;
        for (i = 0; i < 7; i++) begin
            w[i] = q[i+1];
        end
    end
    else w = q;
end

dff_stru dff1(.D(w[7]), .clk(clk), .reset(reset), .Q(q[7]));
dff_stru dff2(.D(w[6]), .clk(clk), .reset(reset), .Q(q[6]));
dff_stru dff3(.D(w[5]), .clk(clk), .reset(reset), .Q(q[5]));
dff_stru dff4(.D(w[4]), .clk(clk), .reset(reset), .Q(q[4]));
dff_stru dff5(.D(w[3]), .clk(clk), .reset(reset), .Q(q[3]));
dff_stru dff6(.D(w[2]), .clk(clk), .reset(reset), .Q(q[2]));
dff_stru dff7(.D(w[1]), .clk(clk), .reset(reset), .Q(q[1]));
dff_stru dff8(.D(w[0]), .clk(clk), .reset(reset), .Q(q[0]));

endmodule

shift_reg_8bit.tb.v
`timescale 1ns/1ps
`include "shift_reg_8bit.v"

module shift_reg_8bit_tb;
reg clk, en, reset, serial_in;
wire serial_out;

shift_reg_8bit dut(.clk(clk), .en(en), .reset(reset), .serial_in(serial_in), .serial_out(serial_out));

initial begin
    clk = 0;
    forever #5 clk = ~clk;
end

initial begin
    $dumpfile("shift_reg_8bit.vcd");
    $dumpvars(0,shift_reg_8bit_tb);
    $display("\t\tTime\t\tserial in\tserial out");
    $monitor($time, "\t\t%b\t\t%b",serial_in,serial_out);
    reset = 1; en = 0; serial_in = 0;
    #10 reset = 0; en = 1;
    #10 serial_in = 1;
    #10 serial_in = 0;
    #10 serial_in = 1;
    #10 serial_in = 1;
    #10 serial_in = 0;
    #10 serial_in = 1;
    #10 serial_in = 0;
    #10 serial_in = 1;
    #10 $finish;
end
    
endmodule

shift_reg_8bit.vcd
$date
	Mon Nov 03 09:05:44 2025
$end
$version
	Icarus Verilog
$end
$timescale
	1ps
$end
$scope module shift_reg_8bit_tb $end
$var wire 1 ! serial_out $end
$var reg 1 " clk $end
$var reg 1 # en $end
$var reg 1 $ reset $end
$var reg 1 % serial_in $end
$scope module dut $end
$var wire 1 " clk $end
$var wire 1 # en $end
$var wire 1 $ reset $end
$var wire 1 % serial_in $end
$var wire 1 ! serial_out $end
$var wire 8 & q [7:0] $end
$var reg 8 ' w [7:0] $end
$var integer 32 ( i [31:0] $end
$scope module dff1 $end
$var wire 1 ) D $end
$var wire 1 " clk $end
$var wire 1 $ reset $end
$var reg 1 * Q $end
$upscope $end
$scope module dff2 $end
$var wire 1 + D $end
$var wire 1 " clk $end
$var wire 1 $ reset $end
$var reg 1 , Q $end
$upscope $end
$scope module dff3 $end
$var wire 1 - D $end
$var wire 1 " clk $end
$var wire 1 $ reset $end
$var reg 1 . Q $end
$upscope $end
$scope module dff4 $end
$var wire 1 / D $end
$var wire 1 " clk $end
$var wire 1 $ reset $end
$var reg 1 0 Q $end
$upscope $end
$scope module dff5 $end
$var wire 1 1 D $end
$var wire 1 " clk $end
$var wire 1 $ reset $end
$var reg 1 2 Q $end
$upscope $end
$scope module dff6 $end
$var wire 1 3 D $end
$var wire 1 " clk $end
$var wire 1 $ reset $end
$var reg 1 4 Q $end
$upscope $end
$scope module dff7 $end
$var wire 1 5 D $end
$var wire 1 " clk $end
$var wire 1 $ reset $end
$var reg 1 6 Q $end
$upscope $end
$scope module dff8 $end
$var wire 1 7 D $end
$var wire 1 " clk $end
$var wire 1 $ reset $end
$var reg 1 8 Q $end
$upscope $end
$upscope $end
$upscope $end
$enddefinitions $end
$comment Show the parameter values. $end
$dumpall
$end
#0
$dumpvars
08
x7
06
x5
04
x3
02
x1
00
x/
0.
x-
0,
x+
0*
x)
bx (
bx '
b0 &
0%
1$
0#
0"
0!
$end
#5000
0)
0+
0-
0/
01
03
05
07
b0 '
1"
#10000
0"
1#
0$
#15000
b111 (
1"
#20000
0"
1%
#25000
1)
b10000000 '
b111 (
1"
#30000
0"
0%
#35000
0)
b10000000 &
1*
b0 '
b111 (
1"
#40000
0"
1%
#45000
1)
b0 &
0*
1+
b11000000 '
b111 (
1"
#50000
0"
#55000
1*
b11000000 &
1,
0+
b10000000 '
b111 (
1"
#60000
0"
0%
#65000
0)
b10000000 &
0,
1+
1-
b1100000 '
b111 (
1"
#70000
0"
1%
#75000
1)
0*
1,
b1100000 &
1.
0-
b11000000 '
b111 (
1"
#80000
0"
0%
#85000
0)
0.
b11000000 &
1*
0+
1-
1/
b110000 '
b111 (
1"
#90000
0"
1%
#95000
1)
0*
0,
1.
b110000 &
10
1+
0/
b11100000 '
b111 (
1"
