up_down_counter.v
module up_down_counter(
    input clk, reset, mode,
    output reg [3:0] count
);

always @(posedge clk or posedge reset) begin
    if (reset) count <= 4'd0;
    else if (mode) count <= count + 4'd1;
    else count <= count - 4'd1;
end
endmodule

up_down_counter.tb.v
`timescale 1ns/1ps
`include "up_down_counter.v"

module up_down_counter_tb;
reg clk, reset, mode;
wire [3:0] count;

up_down_counter dut(.clk(clk), .reset(reset), .mode(mode), .count(count));

initial begin
    clk = 0;
    forever #5 clk = ~clk;
end

initial begin
    $dumpfile("up_down_counter.vcd");
    $dumpvars(0,up_down_counter_tb);
    $display("\t\tTIme\tmode\treset\tcount");
    $monitor($time, "\t%b\t%b\t%d", mode, reset, count);
    reset = 0; mode = 0;
    #10 reset = 1;
    #10 mode = 1;
    #10 reset = 0;
    #100 reset = 1;
    #10 mode = 0;
    #10 reset = 0;
    #100 reset = 1;
    $finish;
end
endmodule

up_down_counter.vcd
$date
	Mon Nov 03 13:32:41 2025
$end
$version
	Icarus Verilog
$end
$timescale
	1ps
$end
$scope module up_down_counter_tb $end
$var wire 4 ! count [3:0] $end
$var reg 1 " clk $end
$var reg 1 # mode $end
$var reg 1 $ reset $end
$scope module dut $end
$var wire 1 " clk $end
$var wire 1 # mode $end
$var wire 1 $ reset $end
$var reg 4 % count [3:0] $end
$upscope $end
$upscope $end
$enddefinitions $end
$comment Show the parameter values. $end
$dumpall
$end
#0
$dumpvars
bx %
0$
0#
0"
bx !
$end
#5000
1"
#10000
b0 !
b0 %
0"
1$
#15000
1"
#20000
0"
1#
#25000
1"
#30000
0"
0$
#35000
b1 !
b1 %
1"
#40000
0"
#45000
b10 !
b10 %
1"
#50000
0"
#55000
b11 !
b11 %
1"
#60000
0"
#65000
b100 !
b100 %
1"
#70000
0"
#75000
b101 !
b101 %
1"
#80000
0"
#85000
b110 !
b110 %
1"
#90000
0"
#95000
b111 !
b111 %
1"
#100000
0"
#105000
b1000 !
b1000 %
1"
#110000
0"
#115000
b1001 !
b1001 %
1"
#120000
0"
#125000
b1010 !
b1010 %
1"
#130000
b0 !
b0 %
0"
1$
#135000
1"
#140000
0"
0#
#145000
1"
#150000
0"
0$
#155000
b1111 !
b1111 %
1"
#160000
0"
#165000
b1110 !
b1110 %
1"
#170000
0"
#175000
b1101 !
b1101 %
1"
#180000
0"
#185000
b1100 !
b1100 %
1"
#190000
0"
#195000
b1011 !
b1011 %
1"
#200000
0"
#205000
b1010 !
b1010 %
1"
#210000
0"
#215000
b1001 !
b1001 %
1"
#220000
0"
#225000
b1000 !
b1000 %
1"
#230000
0"
#235000
b111 !
b111 %
1"
#240000
0"
#245000
b110 !
b110 %
1"
#250000
b0 !
b0 %
0"
1$
